{
  "lastSyncedAt": "2026-05-19T08:24:28.873Z",
  "generatedBy": "scripts/sync_osm.js",
  "overpassEndpoints": [
    "https://overpass-api.de/api/interpreter",
    "https://lz4.overpass-api.de/api/interpreter",
    "https://overpass.kumi.systems/api/interpreter"
  ],
  "overpassSelectedEndpoint": "https://overpass-api.de/api/interpreter",
  "overpassOsmBase": "2026-05-19T08:22:20Z",
  "overpassStatus": [
    {
      "endpoint": "https://overpass-api.de/api/interpreter",
      "host": "overpass-api.de",
      "osmBase": null,
      "statusError": null
    },
    {
      "endpoint": "https://lz4.overpass-api.de/api/interpreter",
      "host": "lz4.overpass-api.de",
      "osmBase": null,
      "statusError": null
    },
    {
      "endpoint": "https://overpass.kumi.systems/api/interpreter",
      "host": "overpass.kumi.systems",
      "osmBase": null,
      "statusError": "Timeout 10000ms"
    }
  ],
  "overpassElements": 111181,
  "rawMapSegments": 15899,
  "keptMapSegments": 14885,
  "keptSegments": 14885,
  "uniqueStreets": 5164
}
